symspell_rust/__init__.py
symspell_rust/symspell_rust.cp39-win_amd64.pyd
symspell_rust-0.3.0.dist-info/LICENSE
symspell_rust-0.3.0.dist-info/METADATA
symspell_rust-0.3.0.dist-info/WHEEL
symspell_rust-0.3.0.dist-info/top_level.txt
symspell_rust-0.3.0.dist-info/RECORD
