Metadata-Version: 2.1
Name: symspell-rust
Version: 0.3.0
Summary: Fast and Accurate SpellChecker
Home-page: https://github.com/zoho-labs/symspell
Author: zoho-labs
License: UNKNOWN
Keywords: Symspell Spellchecker rust python_bind PyO3
Platform: UNKNOWN
